newspaper/__init__.py
newspaper/__main__.py
newspaper/api.py
newspaper/article.py
newspaper/cleaners.py
newspaper/cli.py
newspaper/configuration.py
newspaper/exceptions.py
newspaper/google_news.py
newspaper/mthreading.py
newspaper/network.py
newspaper/nlp.py
newspaper/outputformatters.py
newspaper/parsers.py
newspaper/settings.py
newspaper/source.py
newspaper/text.py
newspaper/urls.py
newspaper/version.py
newspaper/extractors/__init__.py
newspaper/extractors/articlebody_extractor.py
newspaper/extractors/authors_extractor.py
newspaper/extractors/categories_extractor.py
newspaper/extractors/content_extractor.py
newspaper/extractors/defines.py
newspaper/extractors/image_extractor.py
newspaper/extractors/metadata_extractor.py
newspaper/extractors/pubdate_extractor.py
newspaper/extractors/title_extractor.py
newspaper/extractors/videos_extractor.py
newspaper/languages/__init__.py
newspaper/languages/ar.py
newspaper/languages/bn.py
newspaper/languages/hi.py
newspaper/languages/ja.py
newspaper/languages/ko.py
newspaper/languages/my.py
newspaper/languages/ne.py
newspaper/languages/ta.py
newspaper/languages/th.py
newspaper/languages/zh.py
newspaper/resources/misc/google_sources.txt
newspaper/resources/misc/popular_sources.txt
newspaper/resources/misc/useragents.txt
newspaper/resources/text/stopwords-af.txt
newspaper/resources/text/stopwords-ar.txt
newspaper/resources/text/stopwords-as.txt
newspaper/resources/text/stopwords-be.txt
newspaper/resources/text/stopwords-bg.txt
newspaper/resources/text/stopwords-bn.txt
newspaper/resources/text/stopwords-br.txt
newspaper/resources/text/stopwords-ca.txt
newspaper/resources/text/stopwords-cs.txt
newspaper/resources/text/stopwords-cy.txt
newspaper/resources/text/stopwords-da.txt
newspaper/resources/text/stopwords-de.txt
newspaper/resources/text/stopwords-el.txt
newspaper/resources/text/stopwords-en.txt
newspaper/resources/text/stopwords-eo.txt
newspaper/resources/text/stopwords-es.txt
newspaper/resources/text/stopwords-et.txt
newspaper4k-0.9.4.dist-info/METADATA
newspaper4k-0.9.4.dist-info/WHEEL
newspaper4k-0.9.4.dist-info/licenses/LICENSE
newspaper4k-0.9.4.dist-info/RECORD
