Metadata-Version: 2.4
Name: newspaper4k
Version: 0.9.4
Summary: Simplified python article discovery & extraction.
Author-email: Andrei Paraschiv <andrei@thephpfactory.com>
License-Expression: MIT
License-File: LICENSE
Keywords: article,curation,extraction,newspaper,nlp,scraping
Classifier: Development Status :: 4 - Beta
Classifier: Intended Audience :: Developers
Classifier: Intended Audience :: Education
Classifier: Intended Audience :: Information Technology
Classifier: Intended Audience :: Science/Research
Classifier: License :: OSI Approved :: MIT License
Classifier: Natural Language :: English
Classifier: Programming Language :: Python :: 3
Classifier: Topic :: Software Development :: Libraries :: Python Modules
Classifier: Topic :: Text Processing
Classifier: Topic :: Text Processing :: Markup :: HTML
Requires-Python: >=3.10
Requires-Dist: beautifulsoup4>=4.9.3
Requires-Dist: brotli>=1.0.9
Requires-Dist: feedparser>=6.0.2
Requires-Dist: lxml[html-clean]>=5.2.0
Requires-Dist: nltk>=3.6.6
Requires-Dist: pillow>=4.0.0
Requires-Dist: python-dateutil>=2.6.1
Requires-Dist: pyyaml>=5.1
Requires-Dist: requests>=2.26.0
Requires-Dist: tldextract>=2.0.1
Requires-Dist: typing-extensions>=4.10.0
Provides-Extra: all
Requires-Dist: cloudscraper>=1.2.0; extra == 'all'
Requires-Dist: gnews>=0.3.6; extra == 'all'
Requires-Dist: indic-nlp-library>=0.90; extra == 'all'
Requires-Dist: jieba>=0.42.1; extra == 'all'
Requires-Dist: pythainlp>=2.3.2; extra == 'all'
Requires-Dist: tinysegmenter>=0.4; extra == 'all'
Provides-Extra: bn
Requires-Dist: indic-nlp-library>=0.90; extra == 'bn'
Provides-Extra: cloudflare
Requires-Dist: cloudscraper>=1.2.0; extra == 'cloudflare'
Provides-Extra: gnews
Requires-Dist: gnews>=0.3.6; extra == 'gnews'
Provides-Extra: hi
Requires-Dist: indic-nlp-library>=0.90; extra == 'hi'
Provides-Extra: ja
Requires-Dist: tinysegmenter>=0.4; extra == 'ja'
Provides-Extra: np
Requires-Dist: indic-nlp-library>=0.90; extra == 'np'
Provides-Extra: numpy
Requires-Dist: numpy>=1.24; (python_version >= '3.9' and python_version < '3.11') and extra == 'numpy'
Requires-Dist: numpy>=1.25; (python_version >= '3.11') and extra == 'numpy'
Provides-Extra: ta
Requires-Dist: indic-nlp-library>=0.90; extra == 'ta'
Provides-Extra: th
Requires-Dist: pythainlp>=2.3.2; extra == 'th'
Provides-Extra: zh
Requires-Dist: jieba>=0.42.1; extra == 'zh'
